macafm/__init__.py
macafm/__main__.py
macafm/cli.py
macafm/bin/afm
macafm/share/webui/index.html.gz
macafm-0.9.3.dist-info/licenses/LICENSE
macafm-0.9.3.dist-info/METADATA
macafm-0.9.3.dist-info/WHEEL
macafm-0.9.3.dist-info/entry_points.txt
macafm-0.9.3.dist-info/top_level.txt
macafm-0.9.3.dist-info/RECORD
