Metadata-Version: 2.4
Name: macafm
Version: 0.9.3
Summary: Access Apple's on-device Foundation Models via CLI and OpenAI-compatible API
Author-email: Sylvain Cousineau <scouzi1966@users.noreply.github.com>
License-Expression: MIT
Project-URL: Homepage, https://github.com/scouzi1966/maclocal-api
Project-URL: Documentation, https://github.com/scouzi1966/maclocal-api#readme
Project-URL: Repository, https://github.com/scouzi1966/maclocal-api
Project-URL: Issues, https://github.com/scouzi1966/maclocal-api/issues
Keywords: apple,foundation-models,llm,openai,api,macos,apple-silicon,ai,machine-learning,cli
Classifier: Development Status :: 4 - Beta
Classifier: Environment :: Console
Classifier: Environment :: MacOS X
Classifier: Intended Audience :: Developers
Classifier: Operating System :: MacOS :: MacOS X
Classifier: Programming Language :: Python :: 3
Classifier: Programming Language :: Python :: 3.9
Classifier: Programming Language :: Python :: 3.10
Classifier: Programming Language :: Python :: 3.11
Classifier: Programming Language :: Python :: 3.12
Classifier: Programming Language :: Python :: 3.13
Classifier: Topic :: Scientific/Engineering :: Artificial Intelligence
Classifier: Topic :: Software Development :: Libraries :: Python Modules
Requires-Python: >=3.9
License-File: LICENSE
Provides-Extra: dev
Requires-Dist: build; extra == "dev"
Requires-Dist: twine; extra == "dev"
Dynamic: license-file
